{
  "tin": "0333559000073",
  "name": "ดีพร้อมเซ็นเตอร์",
  "aliases": [],
  "directors": [],
  "registeredAt": null,
  "registeredCapital": null,
  "sources": [
    {
      "kind": "contracts-cache",
      "fetchedAt": "2026-07-19T14:38:38.891Z",
      "note": "seed from 291 contract rows · 44 agencies"
    }
  ],
  "seenAgencyIds": [
    "egp-0711",
    "egp-5330701",
    "egp-6330313",
    "egp-6330401",
    "egp-6330402",
    "egp-6330403",
    "egp-6330404",
    "egp-6330406",
    "egp-6330407",
    "egp-6330408",
    "egp-6330409",
    "egp-6330410",
    "egp-6330411",
    "egp-6330412",
    "egp-6330413",
    "egp-6330415",
    "egp-6330418",
    "egp-6330419",
    "egp-6330501",
    "egp-6330504",
    "egp-6330510",
    "egp-6330518",
    "egp-6330520",
    "egp-6330521",
    "egp-6330602",
    "egp-6330605",
    "egp-6330703",
    "egp-6330704",
    "egp-6330708",
    "egp-6330710",
    "egp-6330801",
    "egp-6330803",
    "egp-6330804",
    "egp-6330808",
    "egp-6330906",
    "egp-6331404",
    "egp-6331701",
    "egp-6331702",
    "egp-6331705",
    "egp-6331901",
    "egp-6332102",
    "egp-6340704",
    "egp-6342206",
    "egp-6342605"
  ],
  "contractWinCount": 291,
  "createdAt": "2026-07-19T14:38:38.891Z",
  "updatedAt": "2026-07-19T14:38:38.891Z",
  "confidence": "draft",
  "note": "Open-DBD stub: TIN from e-GP/contracts-cache. Enrich via open refs; verify later with BDEX."
}