{
  "tin": "0453555000272",
  "name": "ห้างหุ้นส่วนจำกัด อาร์พีซี แอสฟัลท์",
  "aliases": [],
  "directors": [],
  "registeredAt": null,
  "registeredCapital": null,
  "sources": [
    {
      "kind": "contracts-cache",
      "fetchedAt": "2026-07-19T14:38:38.891Z",
      "note": "seed from 298 contract rows · 66 agencies"
    }
  ],
  "seenAgencyIds": [
    "egp-0806",
    "egp-0807",
    "egp-2450101",
    "egp-5450101",
    "egp-5450102",
    "egp-5450201",
    "egp-5450203",
    "egp-5450301",
    "egp-5450402",
    "egp-5450403",
    "egp-5450404",
    "egp-5450405",
    "egp-5451102",
    "egp-5451103",
    "egp-5451104",
    "egp-5451301",
    "egp-5451401",
    "egp-6441008",
    "egp-6450101",
    "egp-6450102",
    "egp-6450104",
    "egp-6450105",
    "egp-6450106",
    "egp-6450108",
    "egp-6450109",
    "egp-6450110",
    "egp-6450111",
    "egp-6450203",
    "egp-6450206",
    "egp-6450302",
    "egp-6450304",
    "egp-6450307",
    "egp-6450308",
    "egp-6450402",
    "egp-6450403",
    "egp-6450407",
    "egp-6450504",
    "egp-6450506",
    "egp-6450507",
    "egp-6450602",
    "egp-6450603",
    "egp-6450604",
    "egp-6450605",
    "egp-6450608",
    "egp-6450707",
    "egp-6450907",
    "egp-6451002",
    "egp-6451008",
    "egp-6451108",
    "egp-6451109",
    "egp-6451110",
    "egp-6451111",
    "egp-6451201",
    "egp-6451303",
    "egp-6451401",
    "egp-6451404",
    "egp-6451405",
    "egp-6451406",
    "egp-6451408",
    "egp-6451409",
    "egp-6451410",
    "egp-6451606",
    "egp-6451607",
    "egp-6451608",
    "egp-6451902",
    "egp-6451904"
  ],
  "contractWinCount": 298,
  "createdAt": "2026-07-19T14:38:38.891Z",
  "updatedAt": "2026-07-19T14:38:38.891Z",
  "confidence": "draft",
  "note": "Open-DBD stub: TIN from e-GP/contracts-cache. Enrich via open refs; verify later with BDEX."
}